highway_core/__init__.py
highway_core/cli/engine_cli.py
highway_core/engine/__init__.py
highway_core/engine/engine.py
highway_core/engine/models.py
highway_core/engine/orchestrator.py
highway_core/engine/resource_manager.py
highway_core/engine/state.py
highway_core/engine/sub_workflow_runner.py
highway_core/engine/executors/__init__.py
highway_core/engine/executors/base.py
highway_core/engine/executors/docker.py
highway_core/engine/executors/local_python.py
highway_core/engine/operator_handlers/__init__.py
highway_core/engine/operator_handlers/base_handler.py
highway_core/engine/operator_handlers/condition_handler.py
highway_core/engine/operator_handlers/foreach_handler.py
highway_core/engine/operator_handlers/parallel_handler.py
highway_core/engine/operator_handlers/task_handler.py
highway_core/engine/operator_handlers/wait_handler.py
highway_core/engine/operator_handlers/while_handler.py
highway_core/persistence/__init__.py
highway_core/persistence/database_manager.py
highway_core/persistence/manager.py
highway_core/persistence/models.py
highway_core/persistence/sql_persistence.py
highway_core/tools/__init__.py
highway_core/tools/ansible.py
highway_core/tools/bulkhead.py
highway_core/tools/ci.py
highway_core/tools/command.py
highway_core/tools/decorators.py
highway_core/tools/fetch.py
highway_core/tools/filesystem.py
highway_core/tools/llm.py
highway_core/tools/log.py
highway_core/tools/memory.py
highway_core/tools/registry.py
highway_core/tools/vcs.py
highway_core/utils/__init__.py
highway_core/utils/docker_detector.py
highway_core/utils/naming.py
highway_core-0.2.1.dist-info/licenses/LICENSE
highway_core-0.2.1.dist-info/METADATA
highway_core-0.2.1.dist-info/WHEEL
highway_core-0.2.1.dist-info/entry_points.txt
highway_core-0.2.1.dist-info/top_level.txt
highway_core-0.2.1.dist-info/RECORD
