Metadata-Version: 2.4
Name: highway_core
Version: 0.2.1
Summary: A powerful and flexible workflow engine that enables you to define, execute, and manage complex workflows with ease
Author-email: Farseed Ashouri <farseed.ashouri@gmail.com>
License: MIT License
Project-URL: Homepage, https://github.com/rodmena-limited/highway_core
Project-URL: Issues, https://github.com/rodmena-limited/highway_core/issues
Classifier: Development Status :: 3 - Alpha
Classifier: Intended Audience :: Developers
Classifier: License :: OSI Approved :: MIT License
Classifier: Operating System :: OS Independent
Classifier: Programming Language :: Python :: 3
Classifier: Programming Language :: Python :: 3.10
Classifier: Programming Language :: Python :: 3.11
Classifier: Programming Language :: Python :: 3.12
Classifier: Programming Language :: Python :: 3.13
Classifier: Topic :: Software Development :: Libraries :: Python Modules
Classifier: Topic :: System :: Distributed Computing
Requires-Python: >=3.10
License-File: LICENSE
Requires-Dist: psutil>=7.1.2
Requires-Dist: pyyaml>=6.0
Requires-Dist: requests>=2.28.1
Requires-Dist: pydantic>=2.0.1
Requires-Dist: docker>=7.1.0
Requires-Dist: sqlalchemy>=2.0.15
Requires-Dist: click>=8.0.0
Requires-Dist: importlib-metadata>=4.0.0; python_version < "3.8"
Provides-Extra: dev
Requires-Dist: pytest>=7.0.0; extra == "dev"
Requires-Dist: mypy>=1.0.0; extra == "dev"
Requires-Dist: types-PyYAML>=6.0.0; extra == "dev"
Requires-Dist: types-requests>=2.28.1; extra == "dev"
Requires-Dist: pytest-cov>=2.12.1; extra == "dev"
Requires-Dist: pytest-xdist>=3.0.0; extra == "dev"
Requires-Dist: pytest-asyncio>=0.20.0; extra == "dev"
Requires-Dist: black>=23.1.0; extra == "dev"
Requires-Dist: isort>=5.10.1; extra == "dev"
Dynamic: license-file
